[
{
  "directory": "/home/seed/Computer Graphics/pa1/build",
  "command": "/usr/bin/g++   -isystem /usr/local/include/opencv4  -g   -std=gnu++17 -o CMakeFiles/Rasterizer.dir/main.cpp.o -c \"/home/seed/Computer Graphics/pa1/main.cpp\"",
  "file": "/home/seed/Computer Graphics/pa1/main.cpp"
},
{
  "directory": "/home/seed/Computer Graphics/pa1/build",
  "command": "/usr/bin/g++   -isystem /usr/local/include/opencv4  -g   -std=gnu++17 -o CMakeFiles/Rasterizer.dir/rasterizer.cpp.o -c \"/home/seed/Computer Graphics/pa1/rasterizer.cpp\"",
  "file": "/home/seed/Computer Graphics/pa1/rasterizer.cpp"
},
{
  "directory": "/home/seed/Computer Graphics/pa1/build",
  "command": "/usr/bin/g++   -isystem /usr/local/include/opencv4  -g   -std=gnu++17 -o CMakeFiles/Rasterizer.dir/Triangle.cpp.o -c \"/home/seed/Computer Graphics/pa1/Triangle.cpp\"",
  "file": "/home/seed/Computer Graphics/pa1/Triangle.cpp"
}
]